compair_core/__init__.py
compair_core/api.py
compair_core/db.py
compair_core/compair/__init__.py
compair_core/compair/celery_app.py
compair_core/compair/default_groups.py
compair_core/compair/embeddings.py
compair_core/compair/feedback.py
compair_core/compair/logger.py
compair_core/compair/main.py
compair_core/compair/models.py
compair_core/compair/schema.py
compair_core/compair/tasks.py
compair_core/compair/topic_tags.py
compair_core/compair/utils.py
compair_core/compair_email/__init__.py
compair_core/compair_email/email.py
compair_core/compair_email/email_core.py
compair_core/compair_email/templates.py
compair_core/compair_email/templates_core.py
compair_core/server/__init__.py
compair_core/server/app.py
compair_core/server/deps.py
compair_core/server/settings.py
compair_core/server/local_model/__init__.py
compair_core/server/local_model/app.py
compair_core/server/local_model/ocr.py
compair_core/server/providers/__init__.py
compair_core/server/providers/console_mailer.py
compair_core/server/providers/contracts.py
compair_core/server/providers/http_ocr.py
compair_core/server/providers/local_storage.py
compair_core/server/providers/noop_analytics.py
compair_core/server/providers/noop_billing.py
compair_core/server/providers/noop_ocr.py
compair_core/server/routers/__init__.py
compair_core/server/routers/capabilities.py
compair_core-0.4.22.dist-info/licenses/LICENSE
compair_core-0.4.22.dist-info/METADATA
compair_core-0.4.22.dist-info/WHEEL
compair_core-0.4.22.dist-info/top_level.txt
compair_core-0.4.22.dist-info/RECORD
