Metadata-Version: 2.4
Name: compair-core
Version: 0.4.22
Summary: Open-source foundation of the Compair collaboration platform.
Author: RocketResearch, Inc.
License: MIT
Project-URL: Homepage, https://github.com/RocketResearch-Inc/compair_core
Project-URL: Documentation, https://github.com/RocketResearch-Inc/compair_core
Project-URL: Source, https://github.com/RocketResearch-Inc/compair_core
Requires-Python: >=3.10
License-File: LICENSE
Requires-Dist: fastapi>=0.110
Requires-Dist: uvicorn>=0.29
Requires-Dist: celery>=5.3
Requires-Dist: sqlalchemy>=2.0
Requires-Dist: pgvector>=0.2
Requires-Dist: pydantic>=2.6
Requires-Dist: pydantic-settings>=2.2
Requires-Dist: requests>=2.31
Requires-Dist: httpx>=0.27
Requires-Dist: redis>=5.0
Requires-Dist: psutil>=5.9
Requires-Dist: python-Levenshtein>=0.23
Requires-Dist: redmail>=0.6
Requires-Dist: python-multipart>=0.0.20
Provides-Extra: dev
Requires-Dist: build>=1.0; extra == "dev"
Requires-Dist: twine>=5.0; extra == "dev"
Requires-Dist: pytest>=8.0; extra == "dev"
Requires-Dist: ruff>=0.3; extra == "dev"
Provides-Extra: ocr
Requires-Dist: pillow>=10.0; extra == "ocr"
Requires-Dist: pytesseract>=0.3.10; extra == "ocr"
Requires-Dist: pypdf>=4.0; extra == "ocr"
Provides-Extra: postgres
Requires-Dist: psycopg2-binary>=2.9; extra == "postgres"
Dynamic: license-file
